odoo/addons/l10n_pt_certification/README.md
odoo/addons/l10n_pt_certification/__init__.py
odoo/addons/l10n_pt_certification/__manifest__.py
odoo/addons/l10n_pt_certification/const.py
odoo/addons/l10n_pt_certification/data/template/account.tax-pt.csv
odoo/addons/l10n_pt_certification/data/template/account.tax.group-pt.csv
odoo/addons/l10n_pt_certification/demo/__init__.py
odoo/addons/l10n_pt_certification/demo/account_demo.py
odoo/addons/l10n_pt_certification/demo/ir_config_parameter_data.xml
odoo/addons/l10n_pt_certification/i18n/l10n_pt_certification.pot
odoo/addons/l10n_pt_certification/i18n/pt.po
odoo/addons/l10n_pt_certification/models/__init__.py
odoo/addons/l10n_pt_certification/models/account_move.py
odoo/addons/l10n_pt_certification/models/account_move_send.py
odoo/addons/l10n_pt_certification/models/account_payment.py
odoo/addons/l10n_pt_certification/models/account_payment_method.py
odoo/addons/l10n_pt_certification/models/account_tax.py
odoo/addons/l10n_pt_certification/models/ir_actions_report.py
odoo/addons/l10n_pt_certification/models/l10n_pt_at_series.py
odoo/addons/l10n_pt_certification/models/l10n_pt_attachment.py
odoo/addons/l10n_pt_certification/models/res_company.py
odoo/addons/l10n_pt_certification/models/res_partner.py
odoo/addons/l10n_pt_certification/models/res_product.py
odoo/addons/l10n_pt_certification/models/template_pt.py
odoo/addons/l10n_pt_certification/report/l10n_pt_hash_integrity_templates.xml
odoo/addons/l10n_pt_certification/security/ir.model.access.csv
odoo/addons/l10n_pt_certification/security/l10n_pt_security.xml
odoo/addons/l10n_pt_certification/static/description/icon.png
odoo/addons/l10n_pt_certification/tests/__init__.py
odoo/addons/l10n_pt_certification/tests/common.py
odoo/addons/l10n_pt_certification/tests/test_l10n_pt.py
odoo/addons/l10n_pt_certification/tests/test_taxes_tax_totals_summary.py
odoo/addons/l10n_pt_certification/utils/__init__.py
odoo/addons/l10n_pt_certification/utils/hashing.py
odoo_addon_l10n_pt_certification-18.0.1.0.0.4.dist-info/METADATA
odoo_addon_l10n_pt_certification-18.0.1.0.0.4.dist-info/WHEEL
odoo_addon_l10n_pt_certification-18.0.1.0.0.4.dist-info/top_level.txt
odoo_addon_l10n_pt_certification-18.0.1.0.0.4.dist-info/RECORD
