Metadata-Version: 2.1
Name: odoo-addon-l10n_pt_certification
Version: 18.0.1.0.0.4
Requires-Python: >=3.10
Requires-Dist: odoo-addon-l10n_pt_future_account==18.0.*
Requires-Dist: odoo==18.0.*
Summary: Portugal - Accounting (Certification)
Home-page: https://github.com/OCA/l10n-portugal
License: LGPL-3
Author: Odoo
Classifier: Programming Language :: Python
Classifier: Framework :: Odoo
Classifier: Framework :: Odoo :: 18.0
Classifier: License :: OSI Approved :: GNU Lesser General Public License v3 (LGPLv3)
